certx/__init__.py
certx/server.py
certx/api/__init__.py
certx/api/certificate_api.py
certx/api/certificate_authority_api.py
certx/api/crl_api.py
certx/api/model/__init__.py
certx/api/model/models.py
certx/cmd/__init__.py
certx/cmd/crypto.py
certx/cmd/dbsync.py
certx/common/__init__.py
certx/common/config.py
certx/common/exceptions.py
certx/common/service.py
certx/common/x509_helper.py
certx/common/model/__init__.py
certx/common/model/models.py
certx/conf/__init__.py
certx/conf/database.py
certx/conf/default.py
certx/conf/opts.py
certx/conf/types.py
certx/db/__init__.py
certx/db/api.py
certx/db/migration.py
certx/db/sqlalchemy/__init__.py
certx/db/sqlalchemy/api.py
certx/db/sqlalchemy/migration.py
certx/db/sqlalchemy/models.py
certx/provider/__init__.py
certx/provider/crl_point/__init__.py
certx/provider/crl_point/base.py
certx/provider/crl_point/default.py
certx/provider/crypto/__init__.py
certx/provider/crypto/password.py
certx/provider/key/__init__.py
certx/provider/key/base.py
certx/provider/key/ec.py
certx/provider/key/gm.py
certx/provider/key/rsa.py
certx/provider/x509/__init__.py
certx/provider/x509/base.py
certx/provider/x509/default.py
certx/provider/x509/gm.py
certx/provider/x509/openssl.py
certx/service/__init__.py
certx/service/certificate_service.py
certx/service/resource_service.py
certx/service/impl/__init__.py
certx/service/impl/certificate_service_impl.py
certx/service/impl/resource_service_impl.py
certx/tests/__init__.py
certx/tests/unit/__init__.py
certx/tests/unit/base.py
certx/tests/unit/api/__init__.py
certx/tests/unit/api/test_certificate_api.py
certx/tests/unit/api/test_certificate_authority_api.py
certx/tests/unit/api/test_crl_api.py
certx/tests/unit/common/__init__.py
certx/tests/unit/common/test_x509_helper.py
certx/tests/unit/db/__init__.py
certx/tests/unit/db/base.py
certx/tests/unit/db/utils.py
certx/tests/unit/provider/__init__.py
certx/tests/unit/provider/crl_point/__init__.py
certx/tests/unit/provider/crl_point/test_default.py
certx-0.3.0.dist-info/licenses/LICENSE
certx-0.3.0.dist-info/METADATA
certx-0.3.0.dist-info/WHEEL
certx-0.3.0.dist-info/entry_points.txt
certx-0.3.0.dist-info/top_level.txt
certx-0.3.0.dist-info/RECORD
