Metadata-Version: 2.4
Name: certx
Version: 0.3.0
Summary: Generator Self-Signed Private CA and Certificate
Author: dengshaolin
License: Apache-2.0
Project-URL: Homepage, https://gitee.com/dengshaolin/certx
Project-URL: Bug Tracker, https://gitee.com/dengshaolin/certx/issues
Classifier: Intended Audience :: Information Technology
Classifier: Intended Audience :: System Administrators
Classifier: Operating System :: POSIX :: Linux
Classifier: Operating System :: Microsoft :: Windows
Classifier: Programming Language :: Python
Classifier: Programming Language :: Python :: 3 :: Only
Classifier: Programming Language :: Python :: 3
Classifier: Programming Language :: Python :: 3.9
Classifier: Programming Language :: Python :: 3.10
Classifier: Programming Language :: Python :: 3.11
Classifier: Programming Language :: Python :: 3.12
Classifier: Programming Language :: Python :: 3.13
Requires-Python: >=3.9
License-File: LICENSE
Requires-Dist: cryptography>=45.0.5
Requires-Dist: Flask>=3.1.1
Requires-Dist: flask_restx>=1.3.0
Requires-Dist: marshmallow>=4.0.0
Requires-Dist: oslo.config>=10.0.0
Requires-Dist: oslo.db>=17.3.0
Requires-Dist: oslo.log>=7.2.0
Requires-Dist: pyOpenSSL>=25.1.0
Requires-Dist: SQLAlchemy>=2.0.42
Provides-Extra: test
Requires-Dist: oslotest>=5.0.1; extra == "test"
Provides-Extra: mysql
Requires-Dist: PyMySQL>=1.1.1; extra == "mysql"
Dynamic: license-file
